LEMNS/__init__.py
LEMNS/amplifiers.txt
LEMNS/inverters.txt
LEMNS/lemons.py
LEMNS/negative.txt
LEMNS/positive.txt
LEMNS-1.0.1.dist-info/METADATA
LEMNS-1.0.1.dist-info/WHEEL
LEMNS-1.0.1.dist-info/license.txt
LEMNS-1.0.1.dist-info/top_level.txt
LEMNS-1.0.1.dist-info/RECORD
