Metadata-Version: 2.1
Name: LEMNS
Version: 1.0.1
Summary: an ultra fast sentiment analysis module
Author: 8AAFFF
Author-email: swingyy2@gmail.com
License-File: license.txt
